hackathon_helper/__init__.py
hackathon_helper/api/__init__.py
hackathon_helper/api/api_builder.py
hackathon_helper/api/core_banking.py
hackathon_helper/api/money_movement.py
mctc_hackathon_robot297-0.0.2.dist-info/METADATA
mctc_hackathon_robot297-0.0.2.dist-info/WHEEL
mctc_hackathon_robot297-0.0.2.dist-info/licenses/LICENSE
mctc_hackathon_robot297-0.0.2.dist-info/RECORD
