Metadata-Version: 2.1
Name: mctc_hackathon_robot297
Version: 0.0.2
Summary: Libraries to help with the MCTC Hackathon
Project-URL: Homepage, https://github.com/robot297/Hackathon-Examples
Project-URL: Bug Tracker, https://github.com/robot297/Hackathon-Examples/issues
Author-email: Daniel Obot <danobot@hotmail.com>, Elizabeth Shockey <coffee@snob.beans>
License-File: LICENSE
Classifier: License :: OSI Approved :: MIT License
Classifier: Operating System :: OS Independent
Classifier: Programming Language :: Python :: 3
Requires-Python: >=3.7
Requires-Dist: astroid==2.15.1
Requires-Dist: certifi==2022.12.7
Requires-Dist: charset-normalizer==3.1.0
Requires-Dist: dill==0.3.6
Requires-Dist: idna==3.4
Requires-Dist: isort==5.12.0
Requires-Dist: lazy-object-proxy==1.9.0
Requires-Dist: mccabe==0.7.0
Requires-Dist: platformdirs==3.2.0
Requires-Dist: requests==2.28.2
Requires-Dist: tomli==2.0.1
Requires-Dist: tomlkit==0.11.7
Requires-Dist: typing-extensions==4.5.0
Requires-Dist: urllib3==1.26.15
Requires-Dist: wrapt==1.15.0
